BeautifulSoup.py
MANIFEST.in
README.txt
ez_setup.py
hacker_top.py
pyhackerstories.py
readme.txt
setup.py
hacker_top.egg-info/PKG-INFO
hacker_top.egg-info/SOURCES.txt
hacker_top.egg-info/dependency_links.txt
hacker_top.egg-info/not-zip-safe
hacker_top.egg-info/top_level.txt