Metadata-Version: 1.0
Name: hacker-top
Version: 1.0
Summary: A top-like program for monitoring stories on hacker news.
Home-page: http://www.catonmat.net/blog/follow-hacker-news-from-the-console/
Author: Peteris Krumins
Author-email: peter@catonmat.net
License: GPL
Keywords: hacker news cli
Platform: UNKNOWN
